.gitignore
.gitlab-ci.yml
COPYING
Makefile
README
pyproject.toml
setup.cfg
setup.py
aiobme280/__init__.py
aiobme280/_aiobme280.c
aiobme280/_aiobme280.pyx
aiobme280/error.py
aiobme280/glue.py
aiobme280.egg-info/PKG-INFO
aiobme280.egg-info/SOURCES.txt
aiobme280.egg-info/dependency_links.txt
aiobme280.egg-info/requires.txt
aiobme280.egg-info/top_level.txt
doc/api.rst
doc/changelog.rst
doc/conf.py
doc/conf.rst
doc/index.rst
doc/intro.rst
doc/use.rst
examples/bme280-read.py